agent/__init__.py
agent/config.py
agent/exc.py
agent/globalvar.py
agent/qpagent.py
agent/api/__init__.py
agent/api/api_server.py
agent/api/httpizza.py
agent/handler/__init__.py
agent/handler/agent_master.py
agent/handler/macaca_worker.py
agent/handler/mobile_uirecorder_worker.py
agent/handler/pc_uirecorder_worker.py
agent/util/__init__.py
agent/util/adb.py
agent/util/file.py
agent/util/sys_info.py
slave/__init__.py
slave/config.py
slave/exc.py
slave/globalvar.py
slave/qpagent.py
slave/api/__init__.py
slave/api/api_server.py
slave/api/httpizza.py
slave/handler/__init__.py
slave/handler/agent_master.py
slave/handler/macaca_worker.py
slave/util/__init__.py
slave/util/adb.py
slave/util/file.py
slave/util/sys_info.py
utagent-0.0.86.dist-info/DESCRIPTION.rst
utagent-0.0.86.dist-info/METADATA
utagent-0.0.86.dist-info/RECORD
utagent-0.0.86.dist-info/WHEEL
utagent-0.0.86.dist-info/entry_points.txt
utagent-0.0.86.dist-info/metadata.json
utagent-0.0.86.dist-info/top_level.txt
utagent-0.0.86.dist-info/zip-safe
