Metadata-Version: 2.0
Name: utagent
Version: 0.0.86
Summary: agent
Home-page: UNKNOWN
Author: mafei
Author-email: fei.ma03@ele.me
License: MIT Licence
Platform: any
Requires-Dist: bottle
Requires-Dist: click
Requires-Dist: requests
Requires-Dist: shutit
